webtoon_api/__init__.py
webtoon_api/exceptions.py
webtoon_api/webtoon_api.py
webtoon_api-0.1.0.dist-info/WHEEL
webtoon_api-0.1.0.dist-info/METADATA
webtoon_api-0.1.0.dist-info/RECORD
