Metadata-Version: 2.1
Name: webtoon-api
Version: 0.1.0
Summary: A python library for communicating with non-public Webtoon API.
License: MIT
Author: Your Name
Author-email: you@example.com
Requires-Python: >=3.9,<4.0
Classifier: License :: OSI Approved :: MIT License
Classifier: Programming Language :: Python :: 3
Classifier: Programming Language :: Python :: 3.9
Classifier: Programming Language :: Python :: 3.10
Requires-Dist: pycryptodome (>=3.17,<4.0)
Requires-Dist: requests (>=2.29.0,<3.0.0)
